{
  "sortnum": 1,
  "name": "patchouli.touhou_little_maid.book.entries.overview.world_spawn.name",
  "icon": "touhou_little_maid:fairy_spawn_egg",
  "category": "touhou_little_maid:overview",
  "pages": [
    {
      "type": "text",
      "text": "patchouli.touhou_little_maid.book.entries.overview.world_spawn.pages.0.text"
    },
    {
      "type": "entity",
      "entity": "touhou_little_maid:fairy{OnGround:true}",
      "offset": 0.125,
      "text": "patchouli.touhou_little_maid.book.entries.overview.world_spawn.pages.1.text",
      "anchor": "fairy"
    }
  ]
}