{
  "sortnum": 13,
  "name": "Транспорт",
  "icon": "touhou_little_maid:maid_vehicle",
  "category": "other",
  "pages": [
    {
      "type": "spotlight",
      "item": "touhou_little_maid:maid_vehicle",
      "text": "Транспорт - это серия объектов, где горничные могут управлять ими. Горничная будет управлять им при приближении к $(l)пустому$() транспорту, а затем ближайшая горничная может ездить на транспорте.$(br2)Игроки также могут ездить на этом транспорте, нажав правой кнопкой мыши."
    }
  ]
}