{"format_version":"1.10.0","geometry.model":{"texturewidth":128,"textureheight":128,"visible_bounds_width":3,"visible_bounds_height":2,"visible_bounds_offset":[0,0,0],"bones":[{"name":"head","pivot":[0,18,0],"cubes":[{"origin":[-4,18,-4],"size":[8,8,8],"uv":[0,12]}]},{"name":"blink","parent":"head","pivot":[0,0,0],"cubes":[{"origin":[-4,18,-4.001],"size":[8,8,0],"uv":[45,10]}]},{"name":"hair","parent":"head","pivot":[0,18,4]},{"name":"bone7","parent":"hair","pivot":[0,18,4],"rotation":[10,0,0],"cubes":[{"origin":[3,8,3],"size":[1,10,1],"uv":[32,56]}]},{"name":"bone8","parent":"hair","pivot":[0,18,4],"rotation":[15,0,0],"cubes":[{"origin":[2,8,3],"size":[1,10,1],"uv":[32,56]},{"origin":[0,8,3],"size":[1,10,1],"uv":[32,56]},{"origin":[-4,8,3],"size":[1,10,1],"uv":[32,56]}]},{"name":"bone9","parent":"hair","pivot":[0,18,4],"rotation":[20,0,0],"cubes":[{"origin":[1,8,3],"size":[1,10,1],"uv":[32,56]},{"origin":[-1,8,3],"size":[1,10,1],"uv":[32,56]},{"origin":[-3,8,3],"size":[1,10,1],"uv":[32,56]}]},{"name":"bone12","parent":"hair","pivot":[0,18,4],"rotation":[25,0,0],"cubes":[{"origin":[-2,8,3],"size":[1,10,1],"uv":[32,56]}]},{"name":"hairLeft","parent":"head","pivot":[4,18,-3],"rotation":[-10,0,-10],"cubes":[{"origin":[3.01519,13.17101,-4.03015],"size":[1,5,1],"uv":[0,14]}]},{"name":"hairRight","parent":"head","pivot":[-4,18,-3],"rotation":[-10,0,10],"cubes":[{"origin":[-4.01519,13.17101,-4.03015],"size":[1,5,1],"uv":[0,14]}]},{"name":"headdressLeftTop","parent":"head","pivot":[-1,24.5,4.5],"rotation":[0,10,15],"cubes":[{"origin":[-9,22,4],"size":[8,5,1],"uv":[33,50]}]},{"name":"headdressRightTop","parent":"head","pivot":[1,24.5,4.5],"rotation":[0,-10,-15],"cubes":[{"origin":[1,22,4],"size":[8,5,1],"uv":[0,46]}]},{"name":"headdressLeftBottom","parent":"head","pivot":[0,24,4.5],"rotation":[0,-5,55],"cubes":[{"origin":[1,23,4],"size":[12,4,1],"uv":[39,39]}]},{"name":"headdressRightBottom","parent":"head","pivot":[0,24,4.5],"rotation":[0,5,-55],"cubes":[{"origin":[-13,23,4],"size":[12,4,1],"uv":[34,34]}]},{"name":"headdressMiddle","parent":"head","pivot":[0,25,4.5],"cubes":[{"origin":[-2,22.5,3],"size":[4,5,3],"uv":[50,18]}]},{"name":"hairBack","parent":"head","pivot":[0,24,6],"rotation":[20,0,0],"cubes":[{"origin":[-1,16,4],"size":[2,8,2],"uv":[51,51]}]},{"name":"armRight","pivot":[-3,17.5,0],"rotation":[0,0,25],"cubes":[{"origin":[-5,9.5,-1],"size":[2,8,2],"uv":[0,0]}]},{"name":"bone3","parent":"armRight","pivot":[0,0,-0.5],"cubes":[{"origin":[-5.5,10.5,-1],"size":[3,5,2],"uv":[54,0]}]},{"name":"bone","parent":"bone3","pivot":[0,0,0],"rotation":[-21,0,0],"cubes":[{"origin":[-5.5,9.44423,-6.69644],"size":[3,5,2],"uv":[10,52]}]},{"name":"bone2","parent":"bone3","pivot":[0,0,0],"rotation":[21,0,0],"cubes":[{"origin":[-5.5,9.44423,4.69644],"size":[3,5,2],"uv":[0,52]}]},{"name":"armLeft","pivot":[3,17.5,0],"rotation":[0,0,-25],"cubes":[{"origin":[3,9.5,-1],"size":[2,8,2],"uv":[0,0]}]},{"name":"bone4","parent":"armLeft","pivot":[8,0,-0.5],"cubes":[{"origin":[2.5,10.5,-1],"size":[3,5,2],"uv":[54,0]}]},{"name":"bone5","parent":"bone4","pivot":[8,0,0],"rotation":[-21,0,0],"cubes":[{"origin":[2.5,9.44423,-6.69644],"size":[3,5,2],"uv":[10,52]}]},{"name":"bone6","parent":"bone4","pivot":[8,0,0],"rotation":[21,0,0],"cubes":[{"origin":[2.5,9.44423,4.69644],"size":[3,5,2],"uv":[0,52]}]},{"name":"body","pivot":[0,10.5,0],"cubes":[{"origin":[-3,13.001,-3],"size":[6,5,6],"uv":[0,28]},{"origin":[-2.5,10,-2.5],"size":[5,8,5],"uv":[0,59]},{"origin":[-4,7.999,-2],"size":[8,2,4],"uv":[35,44]}]},{"name":"decoration","parent":"body","pivot":[0,10.5,0],"cubes":[{"origin":[-0.5,16,-3.5],"size":[1,1,1],"uv":[6,0]},{"origin":[-0.5,14,-3.25],"size":[1,2,1],"uv":[4,14],"mirror":true}]},{"name":"bone10","parent":"decoration","pivot":[0,17,-4],"rotation":[0,0,40],"cubes":[{"origin":[-3,16,-3.75],"size":[3,1,1],"uv":[0,12],"mirror":true}]},{"name":"bone11","parent":"decoration","pivot":[0,17,-4],"rotation":[0,0,-40],"cubes":[{"origin":[0,16,-3.75],"size":[3,1,1],"uv":[0,12]}]},{"name":"bone13","parent":"decoration","pivot":[0.5,16,-3],"rotation":[0,0,-27],"cubes":[{"origin":[-0.40798,14.21799,-3.25],"size":[1,2,1],"uv":[4,14],"mirror":true}]},{"name":"bone14","parent":"decoration","pivot":[-0.5,16,-3],"rotation":[0,0,27],"cubes":[{"origin":[-0.59202,14.21799,-3.25],"size":[1,2,1],"uv":[4,14]}]},{"name":"sittingRotationSkirt","parent":"body","pivot":[0,11.5,0],"cubes":[{"origin":[-5,4,-5],"size":[10,2,10],"uv":[0,0]},{"origin":[-4.5,6,-4.5],"size":[9,2,9],"uv":[23,23]},{"origin":[-4,8,-4],"size":[8,2,8],"uv":[30,0]},{"origin":[-3.5,10,-3.5],"size":[7,1,7],"uv":[24,12]},{"origin":[-3,11,-3],"size":[6,1,6],"uv":[0,39]}]},{"name":"legLeft","pivot":[2,9,0],"cubes":[{"origin":[0.5,0,-1.5],"size":[3,9,3],"uv":[21,45]}]},{"name":"legRight","pivot":[-2,9,0],"cubes":[{"origin":[-3.5,0,-1.5],"size":[3,9,3],"uv":[21,45]}]}]}}