{
  "type": "touhou_little_maid:altar_crafting",
  "output": {
    "type": "touhou_little_maid:maid",
    "nbt": {},
    "copy": {
      "ingredient": {
        "item": "touhou_little_maid:film"
      },
      "tag": "MaidInfo"
    }
  },
  "power": 0.5,
  "ingredients": [
    {
      "item": "touhou_little_maid:film"
    },
    {
      "tag": "forge:gems/lapis"
    },
    {
      "tag": "forge:ingots/gold"
    },
    {
      "tag": "forge:dusts/redstone"
    },
    {
      "tag": "forge:ingots/iron"
    },
    {
      "item": "minecraft:coal"
    }
  ]
}